pms_integration_core-25.8.dist-info/licenses/LICENSE.txt
pmsintegration/core/__init__.py
pmsintegration/core/airflow_secret_backend.py
pmsintegration/core/app.py
pmsintegration/core/azure_secret_backend.py
pmsintegration/core/azure_utils.py
pmsintegration/core/cli.py
pmsintegration/core/core_models.py
pmsintegration/core/custom_fields.py
pmsintegration/core/database_cli.py
pmsintegration/core/addepar/__init__.py
pmsintegration/core/addepar/connector/__init__.py
pmsintegration/core/addepar/connector/addepar_config.py
pmsintegration/core/addepar/connector/api_models.py
pmsintegration/core/addepar/connector/client.py
pmsintegration/core/addepar/connector/response_handler.py
pmsintegration/core/azdb/__init__.py
pmsintegration/core/azdb/connector/__init__.py
pmsintegration/core/azdb/connector/databricks_sql_connector.py
pmsintegration/core/cli_commands/__init__.py
pmsintegration/core/cli_commands/addepar_field_mappings.py
pmsintegration/core/cli_commands/pmsdb.py
pmsintegration/core/observability/__init__.py
pmsintegration/core/observability/metrics_core.py
pmsintegration/core/observability/metrics_handler.py
pmsintegration/core/observability/metrics_relay.py
pmsintegration/core/observability/telemetry_service.py
pmsintegration/core/pmsdb/__init__.py
pmsintegration/core/pmsdb/config.py
pmsintegration/core/salesforce/__init__.py
pmsintegration/core/salesforce/events.py
pmsintegration/core/salesforce/sf_event_listener.py
pmsintegration/core/salesforce/sf_event_processor.py
pmsintegration/core/salesforce/sf_utils.py
pmsintegration/core/salesforce/store.py
pmsintegration/core/salesforce/connector/__init__.py
pmsintegration/core/salesforce/connector/pubsub_api_connector.py
pmsintegration/core/salesforce/connector/rest_api_connector.py
pmsintegration/core/salesforce/connector/salesforce_config.py
pmsintegration/core/salesforce/pubsub/__init__.py
pmsintegration/core/salesforce/pubsub/pubsub_utils.py
pmsintegration/core/salesforce/pubsub/types.py
pmsintegration/core/salesforce/pubsub/gen/__init__.py
pms_integration_core-25.8.dist-info/METADATA
pms_integration_core-25.8.dist-info/WHEEL
pms_integration_core-25.8.dist-info/top_level.txt
pms_integration_core-25.8.dist-info/RECORD
